marsutils/__init__.py
marsutils/controlmanager.py
marsutils/decorator.py
marsutils/math.py
marsutils-0.3.1.dist-info/METADATA
marsutils-0.3.1.dist-info/WHEEL
marsutils-0.3.1.dist-info/top_level.txt
marsutils-0.3.1.dist-info/RECORD
