Metadata-Version: 2.1
Name: marsutils
Version: 0.3.1
Summary: Utilities for building frc robots
Home-page: https://github.com/Mars1523/Mars-Utils
Author: Noskcaj19
License: License :: OSI Approved :: MIT License
Platform: UNKNOWN
Classifier: Development Status :: 2 - Pre-Alpha
Classifier: Intended Audience :: Developers
Classifier: License :: OSI Approved :: MIT License
Classifier: Natural Language :: English
Classifier: Programming Language :: Python :: 3
Classifier: Programming Language :: Python :: 3.4
Classifier: Programming Language :: Python :: 3.5
Classifier: Programming Language :: Python :: 3.6
Classifier: Programming Language :: Python :: 3.7
Requires-Dist: pynetworktables
Requires-Dist: robotpy-wpilib-utilities
Requires-Dist: robotpy-hal-base
Requires-Dist: wpilib
